[
  {
    "key": "Mechanical_Engineering",
    "label": "기계공학과"
  },
  {
    "key": "Aerospace_Engineering",
    "label": "항공우주공학과"
  },
  {
    "key": "Naval_Architecture_Ocean_Engineering",
    "label": "조선해양공학과"
  },
  {
    "key": "Industrial_Engineering",
    "label": "산업경영공학과"
  },
  {
    "key": "Chemical_Engineering",
    "label": "화학공학과"
  },
  {
    "key": "Polymer_Science_Engineering",
    "label": "고분자공학과"
  },
  {
    "key": "Materials_Science_Engineering",
    "label": "신소재공학과"
  },
  {
    "key": "Civil_Engineering",
    "label": "사회인프라공학과"
  },
  {
    "key": "Environmental_Engineering",
    "label": "환경공학과"
  },
  {
    "key": "Geoinformatic_Engineering",
    "label": "공간정보공학과"
  },
  {
    "key": "Architectural_Engineering",
    "label": "건축학부(건축공학)"
  },
  {
    "key": "Architecture",
    "label": "건축학부(건축학)"
  },
  {
    "key": "Energy_Resource_Engineering",
    "label": "에너지자원공학과"
  },
  {
    "key": "Convergence_Engineering_Management",
    "label": "융합기술경영학부"
  },
  {
    "key": "Electrical_Engineering",
    "label": "전기공학과"
  },
  {
    "key": "Electronic_Engineering",
    "label": "전자공학과"
  },
  {
    "key": "Information_Communication_Engineering",
    "label": "정보통신공학과"
  },
  {
    "key": "Semiconductor_Systems_Engineering",
    "label": "반도체시스템공학과"
  },
  {
    "key": "Future_Vehicle_Engineering",
    "label": "미래자동차공학(융합전공)"
  },
  {
    "key": "Secondary_Battery_Engineering",
    "label": "이차전지공학(융합전공)"
  },
  {
    "key": "Semiconductor_Engineering",
    "label": "반도체전공(융합전공)"
  }
]